{
  "name": "woomc repo",
  "identifier": "xyz.woomc.repo",
  "iconURL": "https://woomc.xyz/repo/esign/repo_icon.png",
  "website": "https://woomc.xyz/repo",
  "sourceURL": "https://woomc.xyz/repo/esign/source.json",
  "apps": [
    {
      "name": "SoundCloud v8.42.3",
      "bundleIdentifier": "com.soundcloud.TouchApp",
      "developerName": "@woomc on Telegram",
      "iconURL": "https://woomc.xyz/repo/esign/app_icon.png?t=1767296207",
      "localizedDescription": "SoundCloud NoAds - updated to the latest version 8.42.3",
      "subtitle": "Tweaked SoundCloud",
      "tintColor": "#FF5500",
      "versions": [],
      "screenshotURLs": [],
      "version": "8.42.3",
      "versionDate": "2026-01-01T19:36:47Z",
      "size": 103441891,
      "downloadURL": "https://github.com/Random32352-sys/Feather-Esign-Repo-TG-Bot/releases/download/v8.42.3/soundcloud.ipa?t=1767296207"
    },
    {
      "name": "Coming Soon",
      "bundleIdentifier": "com.placeholder.app",
      "developerName": "woomc",
      "iconURL": "https://woomc.xyz/repo/esign/app_icon.png?t=1767296207",
      "localizedDescription": "More apps will be added here soon!",
      "subtitle": "Stay tuned",
      "tintColor": "#808080",
      "versions": [
        {
          "version": "1.0",
          "date": "2026-01-01T19:32:07Z",
          "size": 0,
          "downloadURL": "https://woomc.xyz/repo/esign/placeholder.ipa?t=1767296207"
        }
      ],
      "screenshotURLs": [],
      "version": "1.0",
      "versionDate": "2026-01-01T19:32:07Z",
      "size": 0,
      "downloadURL": "https://woomc.xyz/repo/esign/placeholder.ipa?t=1767296207"
    }
  ],
  "news": []
}